custom_nn_implementation/custom_nn_implementation.srcs/sources_1/new/relu.v
module relu #(
  parameter DATAWIDTH      = 16,
  parameter WEIGHTINTWIDTH = 4
)(
  input                        clk,
  input      [2*DATAWIDTH-1:0] x,
  output reg [DATAWIDTH-1:0]   out
);

always @(posedge clk) begin
  if ($signed(x) >= 0) begin
    if (|x[2*DATAWIDTH-1 -: WEIGHTINTWIDTH+1]) 
      out <= {1'b0, {(DATAWIDTH-1){1'b1}}};    
    else
      out <= x[2*DATAWIDTH-1 - WEIGHTINTWIDTH -: DATAWIDTH];
  end else begin
    out <= 0;
  end
end

endmodule

custom_nn_implementation/custom_nn_implementation.srcs/sources_1/new/weight_memory.v
`timescale 1ns / 1ps

module weight_memory #(
  parameter NUMWEIGHT     = 3,
  parameter NEURONNO      = 5,
  parameter LAYERNO       = 1,
  parameter ADDRESSWIDTH  = 10,
  parameter DATAWIDTH     = 16,
  parameter WEIGHTFILE    = "w_1_15.mif"
)(
  input                         clk,
  input                         ren,
  input      [ADDRESSWIDTH-1:0] radd,
  output reg [DATAWIDTH-1:0]    wout
);

  reg [DATAWIDTH-1:0] mem [0:NUMWEIGHT-1];

  initial begin
    $readmemb(WEIGHTFILE, mem);
  end

  always @(posedge clk) begin
    if (ren) begin
      wout <= mem[radd];
    end
  end

endmodule

custom_nn_implementation/custom_nn_implementation.srcs/sources_1/new/neuron_1.v
`timescale 1ns / 1ps

module neuron #(
  parameter NUM_INPUTS      = 784,
  parameter DATAWIDTH       = 16,
  parameter WEIGHTINTWIDTH  = 1,
  parameter BIAS            = 0,
  parameter WEIGHTFILE      = ""
)(
  input                      clk,
  input                      rst,
  input  [DATAWIDTH-1:0]     input_val,
  input                      input_valid,
  output [DATAWIDTH-1:0]     out,
  output reg                 out_valid
);

  localparam ADDR_WIDTH = $clog2(NUM_INPUTS);
  
  wire                       read_en;
  wire [DATAWIDTH-1:0]       weight;
  wire                       mux_valid;
  wire [2*DATAWIDTH:0]       combo_sum;
  wire [2*DATAWIDTH:0]       biased_sum;
  
  reg  [ADDR_WIDTH:0]        input_index;
  (* use_dsp48 = "yes" *)reg  [2*DATAWIDTH-1:0]     product;
  reg  [2*DATAWIDTH-1:0]     sum;
  reg  [2*DATAWIDTH-1:0]     bias;
  reg                        input_valid_d1;
  reg                        input_valid_d2;
  reg                        sigvalid;
  reg  [DATAWIDTH-1:0]       input_reg;
  reg                        muxvalid_d;
  reg                        muxvalid_f;              // end_of_dot_d
  
  initial begin
    bias = {BIAS[DATAWIDTH-1:0], {DATAWIDTH{1'b0}}};
  end

  assign read_en    = input_valid;
  assign combo_sum  = sum + product;
  assign biased_sum = sum + bias;
  assign mux_valid  = input_valid_d2;
  
  always @(posedge clk) begin
    if (rst | out_valid)
      input_index <= 0;
    else if (input_valid)
      input_index <= input_index + 1;
  end
  
  always @(posedge clk) begin
    product <= $signed(input_reg) * $signed(weight);
  end
  
  always @(posedge clk) begin
    if (rst | out_valid) begin
      sum <= 0;
    end
    else if ((input_index == NUM_INPUTS) && muxvalid_f) begin
      sum <= (biased_sum[2*DATAWIDTH] != biased_sum[2*DATAWIDTH-1]) ? {biased_sum[2*DATAWIDTH], {2*DATAWIDTH-1{biased_sum[2*DATAWIDTH-1]}}} : biased_sum;
    end
    else if (mux_valid) begin
      sum <= (combo_sum[2*DATAWIDTH] != combo_sum[2*DATAWIDTH-1]) ? {combo_sum[2*DATAWIDTH], {2*DATAWIDTH-1{combo_sum[2*DATAWIDTH-1]}}} : combo_sum;
    end
  end
  
  always @(posedge clk) begin
    input_reg      <= input_val;
    input_valid_d1 <= input_valid;
    input_valid_d2 <= input_valid_d1;
    
    sigvalid       <= ((input_index == NUM_INPUTS) & muxvalid_f);
    out_valid      <= sigvalid;
    muxvalid_d     <= mux_valid;
    muxvalid_f     <= !mux_valid & muxvalid_d;
    
  end
  
  weight_memory #(
    .NUMWEIGHT     (NUM_INPUTS),
    .ADDRESSWIDTH  (ADDR_WIDTH),
    .DATAWIDTH     (DATAWIDTH),
    .WEIGHTFILE    (WEIGHTFILE)
  ) weight_mem (
    .clk           (clk),
    .ren           (read_en),
    .radd          (input_index),
    .wout          (weight)
  );

  relu #(
    .DATAWIDTH      (DATAWIDTH),
    .WEIGHTINTWIDTH (WEIGHTINTWIDTH)
  ) relu_act (
    .clk            (clk),
    .x              (sum),
    .out            (out)
  );
  
endmodule

custom_nn_implementation/layer_4.v
`timescale 1ns / 1ps

module layer_4 #(
  parameter NUM_INPUTS      = 10,
  parameter DATAWIDTH       = 16,
  parameter WEIGHTINTWIDTH  = 4
)(
  input                        clk,
  input                        rst,
  input                        input_valid,
  input  [DATAWIDTH-1:0]       input_val,
  output [DATAWIDTH*10-1:0]   x_out,
  output [9:0]             o_valid
);

  neuron #(
    .NUM_INPUTS      (NUM_INPUTS),
    .DATAWIDTH       (DATAWIDTH),
    .WEIGHTINTWIDTH  (WEIGHTINTWIDTH),
    .BIAS            (16'b1111110011000010),
    .WEIGHTFILE      ("w_4_0.mif")
  ) n_0 (
    .clk             (clk),
    .rst             (rst),
    .input_val       (input_val),
    .input_valid     (input_valid),
    .out             (x_out[0*DATAWIDTH+:DATAWIDTH]),
    .out_valid       (o_valid[0])
  );

  neuron #(
    .NUM_INPUTS      (NUM_INPUTS),
    .DATAWIDTH       (DATAWIDTH),
    .WEIGHTINTWIDTH  (WEIGHTINTWIDTH),
    .BIAS            (16'b1111111100000110),
    .WEIGHTFILE      ("w_4_1.mif")
  ) n_1 (
    .clk             (clk),
    .rst             (rst),
    .input_val       (input_val),
    .input_valid     (input_valid),
    .out             (x_out[1*DATAWIDTH+:DATAWIDTH]),
    .out_valid       (o_valid[1])
  );

  neuron #(
    .NUM_INPUTS      (NUM_INPUTS),
    .DATAWIDTH       (DATAWIDTH),
    .WEIGHTINTWIDTH  (WEIGHTINTWIDTH),
    .BIAS            (16'b0000011101110000),
    .WEIGHTFILE      ("w_4_2.mif")
  ) n_2 (
    .clk             (clk),
    .rst             (rst),
    .input_val       (input_val),
    .input_valid     (input_valid),
    .out             (x_out[2*DATAWIDTH+:DATAWIDTH]),
    .out_valid       (o_valid[2])
  );

  neuron #(
    .NUM_INPUTS      (NUM_INPUTS),
    .DATAWIDTH       (DATAWIDTH),
    .WEIGHTINTWIDTH  (WEIGHTINTWIDTH),
    .BIAS            (16'b1111101101101100),
    .WEIGHTFILE      ("w_4_3.mif")
  ) n_3 (
    .clk             (clk),
    .rst             (rst),
    .input_val       (input_val),
    .input_valid     (input_valid),
    .out             (x_out[3*DATAWIDTH+:DATAWIDTH]),
    .out_valid       (o_valid[3])
  );

  neuron #(
    .NUM_INPUTS      (NUM_INPUTS),
    .DATAWIDTH       (DATAWIDTH),
    .WEIGHTINTWIDTH  (WEIGHTINTWIDTH),
    .BIAS            (16'b1111111000101111),
    .WEIGHTFILE      ("w_4_4.mif")
  ) n_4 (
    .clk             (clk),
    .rst             (rst),
    .input_val       (input_val),
    .input_valid     (input_valid),
    .out             (x_out[4*DATAWIDTH+:DATAWIDTH]),
    .out_valid       (o_valid[4])
  );

  neuron #(
    .NUM_INPUTS      (NUM_INPUTS),
    .DATAWIDTH       (DATAWIDTH),
    .WEIGHTINTWIDTH  (WEIGHTINTWIDTH),
    .BIAS            (16'b1111111100010011),
    .WEIGHTFILE      ("w_4_5.mif")
  ) n_5 (
    .clk             (clk),
    .rst             (rst),
    .input_val       (input_val),
    .input_valid     (input_valid),
    .out             (x_out[5*DATAWIDTH+:DATAWIDTH]),
    .out_valid       (o_valid[5])
  );

  neuron #(
    .NUM_INPUTS      (NUM_INPUTS),
    .DATAWIDTH       (DATAWIDTH),
    .WEIGHTINTWIDTH  (WEIGHTINTWIDTH),
    .BIAS            (16'b1111101101000100),
    .WEIGHTFILE      ("w_4_6.mif")
  ) n_6 (
    .clk             (clk),
    .rst             (rst),
    .input_val       (input_val),
    .input_valid     (input_valid),
    .out             (x_out[6*DATAWIDTH+:DATAWIDTH]),
    .out_valid       (o_valid[6])
  );

  neuron #(
    .NUM_INPUTS      (NUM_INPUTS),
    .DATAWIDTH       (DATAWIDTH),
    .WEIGHTINTWIDTH  (WEIGHTINTWIDTH),
    .BIAS            (16'b1111100110101111),
    .WEIGHTFILE      ("w_4_7.mif")
  ) n_7 (
    .clk             (clk),
    .rst             (rst),
    .input_val       (input_val),
    .input_valid     (input_valid),
    .out             (x_out[7*DATAWIDTH+:DATAWIDTH]),
    .out_valid       (o_valid[7])
  );

  neuron #(
    .NUM_INPUTS      (NUM_INPUTS),
    .DATAWIDTH       (DATAWIDTH),
    .WEIGHTINTWIDTH  (WEIGHTINTWIDTH),
    .BIAS            (16'b0000010010111010),
    .WEIGHTFILE      ("w_4_8.mif")
  ) n_8 (
    .clk             (clk),
    .rst             (rst),
    .input_val       (input_val),
    .input_valid     (input_valid),
    .out             (x_out[8*DATAWIDTH+:DATAWIDTH]),
    .out_valid       (o_valid[8])
  );

  neuron #(
    .NUM_INPUTS      (NUM_INPUTS),
    .DATAWIDTH       (DATAWIDTH),
    .WEIGHTINTWIDTH  (WEIGHTINTWIDTH),
    .BIAS            (16'b0000010001011100),
    .WEIGHTFILE      ("w_4_9.mif")
  ) n_9 (
    .clk             (clk),
    .rst             (rst),
    .input_val       (input_val),
    .input_valid     (input_valid),
    .out             (x_out[9*DATAWIDTH+:DATAWIDTH]),
    .out_valid       (o_valid[9])
  );

endmodule

custom_nn_implementation/custom_nn_implementation.srcs/sim_1/new/tb_layer.sv
`timescale 1ns / 1ps

module tb_layer_4();

    // Parameters
    parameter NUM_INPUTS   = 10;
    parameter DATAWIDTH    = 16;
    parameter WEIGHTINTWIDTH = 4;
    parameter CLOCK_PERIOD = 10;  // 100 MHz clock
    parameter NUM_NEURONS  = 10;
  
    // Signals
    reg                                     clk;
    reg                                     rst;
    reg                                     input_valid;
    reg        [DATAWIDTH-1:0]              input_val;
    wire       [DATAWIDTH*10-1:0]           x_out;
    wire       [9:0]                        o_valid;
  
    // Testbench variables
    integer i;
  
    // Instantiate DUT
    layer_4 #(
        .NUM_INPUTS     (NUM_INPUTS),
        .DATAWIDTH      (DATAWIDTH),
        .WEIGHTINTWIDTH (WEIGHTINTWIDTH)
    ) dut (
        .clk            (clk),
        .rst            (rst),
        .input_valid    (input_valid),
        .input_val      (input_val),
        .x_out          (x_out),
        .o_valid        (o_valid)
    );
  
    // Clock generation
    initial begin
        clk = 0;
        forever #(CLOCK_PERIOD/2) clk = ~clk;
    end
  
    // Main test sequence
    initial begin
        // Initialize signals
        rst         = 1;
        input_valid = 0;
        input_val   = 0;
    
        // Reset sequence
        #(CLOCK_PERIOD*5);
        rst = 0;
        #(CLOCK_PERIOD*5);
    
        $display("[%0t] Starting test for layer_4", $time);
    
        // Feed input data
        $display("[%0t] Applying input sequence...", $time);
        input_valid = 1;
        for (i = 0; i < NUM_INPUTS; i = i + 1) begin
            // Input values 1, 2, 3, ... 10
            input_val = i + 1;
            #CLOCK_PERIOD;
            $display("[%0t] Input %2d: %4d (0x%4h)", $time, i, input_val, input_val);
        end
        input_valid = 0;
    
        // Wait for all outputs to be ready
        $display("[%0t] Waiting for outputs...", $time);
        wait (o_valid == 10'b1111111111);
    
        // Display and verify outputs
        $display("\n[%0t] All outputs valid:", $time);
        for (i = 0; i < NUM_NEURONS; i = i + 1) begin
            $display("  Neuron %0d: %4d (0x%4h)", i, $signed(x_out[i*DATAWIDTH +: DATAWIDTH]), x_out[i*DATAWIDTH +: DATAWIDTH]);
        end
    
        $display("\n[%0t] TEST COMPLETED", $time);
        $finish;
    end
  
    // Timeout watchdog
    initial begin
        #(CLOCK_PERIOD * (NUM_INPUTS * 10 + 500));  // Allow extra cycles
        $display("\n[%0t] ERROR: Simulation timed out!", $time);
        $display("Current o_valid: %10b", o_valid);
        $finish;
    end
  
    // Waveform dumping
    initial begin
        $dumpfile("tb_layer_4.vcd");
        $dumpvars(0, tb_layer_4);
    end
endmodule

custom_nn_implementation/custom_nn_implementation.sim/sim_1/behav/xsim/tb_layer_4.vcd
$date
   Tue Aug  5 23:18:09 2025
$end

$version
  2023.2
  $dumpfile ("tb_layer_4.vcd") 
$end

$timescale
  1ps
$end

$scope module tb_layer_4 $end
$var reg 1 ! clk $end
$var reg 1 " rst $end
$var reg 1 # input_valid $end
$var reg 16 $ input_val [15:0] $end
$var wire 160 % x_out [159:0] $end
$var wire 10 & o_valid [9:0] $end
$var integer 32 ' i [31:0] $end
$scope module dut $end
$var wire 1 ( clk $end
$var wire 1 ) rst $end
$var wire 1 * input_valid $end
$var wire 16 + input_val [15:0] $end
$var wire 160 % x_out [159:0] $end
$var wire 10 & o_valid [9:0] $end
$scope module n_0 $end
$var wire 1 ( clk $end
$var wire 1 ) rst $end
$var wire 16 + input_val [15:0] $end
$var wire 1 * input_valid $end
$var wire 16 , out [15:0] $end
$var reg 1 - out_valid $end
$var wire 1 . read_en $end
$var wire 16 / weight [15:0] $end
$var wire 1 0 mux_valid $end
$var wire 33 1 combo_sum [32:0] $end
$var wire 33 2 biased_sum [32:0] $end
$var reg 5 3 input_index [4:0] $end
$var reg 32 4 product [31:0] $end
$var reg 32 5 sum [31:0] $end
$var reg 32 6 bias [31:0] $end
$var reg 1 7 input_valid_d1 $end
$var reg 1 8 input_valid_d2 $end
$var reg 1 9 sigvalid $end
$var reg 16 : input_reg [15:0] $end
$var reg 1 ; muxvalid_d $end
$var reg 1 < muxvalid_f $end
$scope module weight_mem $end
$var wire 1 ( clk $end
$var wire 1 . ren $end
$var wire 4 = radd [3:0] $end
$var reg 16 > wout [15:0] $end
$upscope $end
$scope module relu_act $end
$var wire 1 ( clk $end
$var wire 32 ? x [31:0] $end
$var reg 16 @ out [15:0] $end
$upscope $end
$upscope $end
$scope module n_1 $end
$var wire 1 ( clk $end
$var wire 1 ) rst $end
$var wire 16 + input_val [15:0] $end
$var wire 1 * input_valid $end
$var wire 16 , out [15:0] $end
$var reg 1 A out_valid $end
$var wire 1 B read_en $end
$var wire 16 C weight [15:0] $end
$var wire 1 D mux_valid $end
$var wire 33 E combo_sum [32:0] $end
$var wire 33 F biased_sum [32:0] $end
$var reg 5 G input_index [4:0] $end
$var reg 32 H product [31:0] $end
$var reg 32 I sum [31:0] $end
$var reg 32 J bias [31:0] $end
$var reg 1 K input_valid_d1 $end
$var reg 1 L input_valid_d2 $end
$var reg 1 M sigvalid $end
$var reg 16 N input_reg [15:0] $end
$var reg 1 O muxvalid_d $end
$var reg 1 P muxvalid_f $end
$scope module weight_mem $end
$var wire 1 ( clk $end
$var wire 1 B ren $end
$var wire 4 Q radd [3:0] $end
$var reg 16 R wout [15:0] $end
$upscope $end
$scope module relu_act $end
$var wire 1 ( clk $end
$var wire 32 S x [31:0] $end
$var reg 16 T out [15:0] $end
$upscope $end
$upscope $end
$scope module n_2 $end
$var wire 1 ( clk $end
$var wire 1 ) rst $end
$var wire 16 + input_val [15:0] $end
$var wire 1 * input_valid $end
$var wire 16 , out [15:0] $end
$var reg 1 U out_valid $end
$var wire 1 V read_en $end
$var wire 16 W weight [15:0] $end
$var wire 1 X mux_valid $end
$var wire 33 Y combo_sum [32:0] $end
$var wire 33 Z biased_sum [32:0] $end
$var reg 5 [ input_index [4:0] $end
$var reg 32 \ product [31:0] $end
$var reg 32 ] sum [31:0] $end
$var reg 32 ^ bias [31:0] $end
$var reg 1 _ input_valid_d1 $end
$var reg 1 ` input_valid_d2 $end
$var reg 1 a sigvalid $end
$var reg 16 b input_reg [15:0] $end
$var reg 1 c muxvalid_d $end
$var reg 1 d muxvalid_f $end
$scope module weight_mem $end
$var wire 1 ( clk $end
$var wire 1 V ren $end
$var wire 4 e radd [3:0] $end
$var reg 16 f wout [15:0] $end
$upscope $end
$scope module relu_act $end
$var wire 1 ( clk $end
$var wire 32 g x [31:0] $end
$var reg 16 h out [15:0] $end
$upscope $end
$upscope $end
$scope module n_3 $end
$var wire 1 ( clk $end
$var wire 1 ) rst $end
$var wire 16 + input_val [15:0] $end
$var wire 1 * input_valid $end
$var wire 16 , out [15:0] $end
$var reg 1 i out_valid $end
$var wire 1 j read_en $end
$var wire 16 k weight [15:0] $end
$var wire 1 l mux_valid $end
$var wire 33 m combo_sum [32:0] $end
$var wire 33 n biased_sum [32:0] $end
$var reg 5 o input_index [4:0] $end
$var reg 32 p product [31:0] $end
$var reg 32 q sum [31:0] $end
$var reg 32 r bias [31:0] $end
$var reg 1 s input_valid_d1 $end
$var reg 1 t input_valid_d2 $end
$var reg 1 u sigvalid $end
$var reg 16 v input_reg [15:0] $end
$var reg 1 w muxvalid_d $end
$var reg 1 x muxvalid_f $end
$scope module weight_mem $end
$var wire 1 ( clk $end
$var wire 1 j ren $end
$var wire 4 y radd [3:0] $end
$var reg 16 z wout [15:0] $end
$upscope $end
$scope module relu_act $end
$var wire 1 ( clk $end
$var wire 32 { x [31:0] $end
$var reg 16 | out [15:0] $end
$upscope $end
$upscope $end
$scope module n_4 $end
$var wire 1 ( clk $end
$var wire 1 ) rst $end
$var wire 16 + input_val [15:0] $end
$var wire 1 * input_valid $end
$var wire 16 , out [15:0] $end
$var reg 1 } out_valid $end
$var wire 1 ~ read_en $end
$var wire 16 !! weight [15:0] $end
$var wire 1 "! mux_valid $end
$var wire 33 #! combo_sum [32:0] $end
$var wire 33 $! biased_sum [32:0] $end
$var reg 5 %! input_index [4:0] $end
$var reg 32 &! product [31:0] $end
$var reg 32 '! sum [31:0] $end
$var reg 32 (! bias [31:0] $end
$var reg 1 )! input_valid_d1 $end
$var reg 1 *! input_valid_d2 $end
$var reg 1 +! sigvalid $end
$var reg 16 ,! input_reg [15:0] $end
$var reg 1 -! muxvalid_d $end
$var reg 1 .! muxvalid_f $end
$scope module weight_mem $end
$var wire 1 ( clk $end
$var wire 1 ~ ren $end
$var wire 4 /! radd [3:0] $end
$var reg 16 0! wout [15:0] $end
$upscope $end
$scope module relu_act $end
$var wire 1 ( clk $end
$var wire 32 1! x [31:0] $end
$var reg 16 2! out [15:0] $end
$upscope $end
$upscope $end
$scope module n_5 $end
$var wire 1 ( clk $end
$var wire 1 ) rst $end
$var wire 16 + input_val [15:0] $end
$var wire 1 * input_valid $end
$var wire 16 , out [15:0] $end
$var reg 1 3! out_valid $end
$var wire 1 4! read_en $end
$var wire 16 5! weight [15:0] $end
$var wire 1 6! mux_valid $end
$var wire 33 7! combo_sum [32:0] $end
$var wire 33 8! biased_sum [32:0] $end
$var reg 5 9! input_index [4:0] $end
$var reg 32 :! product [31:0] $end
$var reg 32 ;! sum [31:0] $end
$var reg 32 <! bias [31:0] $end
$var reg 1 =! input_valid_d1 $end
$var reg 1 >! input_valid_d2 $end
$var reg 1 ?! sigvalid $end
$var reg 16 @! input_reg [15:0] $end
$var reg 1 A! muxvalid_d $end
$var reg 1 B! muxvalid_f $end
$scope module weight_mem $end
$var wire 1 ( clk $end
$var wire 1 4! ren $end
$var wire 4 C! radd [3:0] $end
$var reg 16 D! wout [15:0] $end
$upscope $end
$scope module relu_act $end
$var wire 1 ( clk $end
$var wire 32 E! x [31:0] $end
$var reg 16 F! out [15:0] $end
$upscope $end
$upscope $end
$scope module n_6 $end
$var wire 1 ( clk $end
$var wire 1 ) rst $end
$var wire 16 + input_val [15:0] $end
$var wire 1 * input_valid $end
$var wire 16 , out [15:0] $end
$var reg 1 G! out_valid $end
$var wire 1 H! read_en $end
$var wire 16 I! weight [15:0] $end
$var wire 1 J! mux_valid $end
$var wire 33 K! combo_sum [32:0] $end
$var wire 33 L! biased_sum [32:0] $end
$var reg 5 M! input_index [4:0] $end
$var reg 32 N! product [31:0] $end
$var reg 32 O! sum [31:0] $end
$var reg 32 P! bias [31:0] $end
$var reg 1 Q! input_valid_d1 $end
$var reg 1 R! input_valid_d2 $end
$var reg 1 S! sigvalid $end
$var reg 16 T! input_reg [15:0] $end
$var reg 1 U! muxvalid_d $end
$var reg 1 V! muxvalid_f $end
$scope module weight_mem $end
$var wire 1 ( clk $end
$var wire 1 H! ren $end
$var wire 4 W! radd [3:0] $end
$var reg 16 X! wout [15:0] $end
$upscope $end
$scope module relu_act $end
$var wire 1 ( clk $end
$var wire 32 Y! x [31:0] $end
$var reg 16 Z! out [15:0] $end
$upscope $end
$upscope $end
$scope module n_7 $end
$var wire 1 ( clk $end
$var wire 1 ) rst $end
$var wire 16 + input_val [15:0] $end
$var wire 1 * input_valid $end
$var wire 16 , out [15:0] $end
$var reg 1 [! out_valid $end
$var wire 1 \! read_en $end
$var wire 16 ]! weight [15:0] $end
$var wire 1 ^! mux_valid $end
$var wire 33 _! combo_sum [32:0] $end
$var wire 33 `! biased_sum [32:0] $end
$var reg 5 a! input_index [4:0] $end
$var reg 32 b! product [31:0] $end
$var reg 32 c! sum [31:0] $end
$var reg 32 d! bias [31:0] $end
$var reg 1 e! input_valid_d1 $end
$var reg 1 f! input_valid_d2 $end
$var reg 1 g! sigvalid $end
$var reg 16 h! input_reg [15:0] $end
$var reg 1 i! muxvalid_d $end
$var reg 1 j! muxvalid_f $end
$scope module weight_mem $end
$var wire 1 ( clk $end
$var wire 1 \! ren $end
$var wire 4 k! radd [3:0] $end
$var reg 16 l! wout [15:0] $end
$upscope $end
$scope module relu_act $end
$var wire 1 ( clk $end
$var wire 32 m! x [31:0] $end
$var reg 16 n! out [15:0] $end
$upscope $end
$upscope $end
$scope module n_8 $end
$var wire 1 ( clk $end
$var wire 1 ) rst $end
$var wire 16 + input_val [15:0] $end
$var wire 1 * input_valid $end
$var wire 16 , out [15:0] $end
$var reg 1 o! out_valid $end
$var wire 1 p! read_en $end
$var wire 16 q! weight [15:0] $end
$var wire 1 r! mux_valid $end
$var wire 33 s! combo_sum [32:0] $end
$var wire 33 t! biased_sum [32:0] $end
$var reg 5 u! input_index [4:0] $end
$var reg 32 v! product [31:0] $end
$var reg 32 w! sum [31:0] $end
$var reg 32 x! bias [31:0] $end
$var reg 1 y! input_valid_d1 $end
$var reg 1 z! input_valid_d2 $end
$var reg 1 {! sigvalid $end
$var reg 16 |! input_reg [15:0] $end
$var reg 1 }! muxvalid_d $end
$var reg 1 ~! muxvalid_f $end
$scope module weight_mem $end
$var wire 1 ( clk $end
$var wire 1 p! ren $end
$var wire 4 !" radd [3:0] $end
$var reg 16 "" wout [15:0] $end
$upscope $end
$scope module relu_act $end
$var wire 1 ( clk $end
$var wire 32 #" x [31:0] $end
$var reg 16 $" out [15:0] $end
$upscope $end
$upscope $end
$scope module n_9 $end
$var wire 1 ( clk $end
$var wire 1 ) rst $end
$var wire 16 + input_val [15:0] $end
$var wire 1 * input_valid $end
$var wire 16 , out [15:0] $end
$var reg 1 %" out_valid $end
$var wire 1 &" read_en $end
$var wire 16 '" weight [15:0] $end
$var wire 1 (" mux_valid $end
$var wire 33 )" combo_sum [32:0] $end
$var wire 33 *" biased_sum [32:0] $end
$var reg 5 +" input_index [4:0] $end
$var reg 32 ," product [31:0] $end
$var reg 32 -" sum [31:0] $end
$var reg 32 ." bias [31:0] $end
$var reg 1 /" input_valid_d1 $end
$var reg 1 0" input_valid_d2 $end
$var reg 1 1" sigvalid $end
$var reg 16 2" input_reg [15:0] $end
$var reg 1 3" muxvalid_d $end
$var reg 1 4" muxvalid_f $end
$scope module weight_mem $end
$var wire 1 ( clk $end
$var wire 1 &" ren $end
$var wire 4 5" radd [3:0] $end
$var reg 16 6" wout [15:0] $end
$upscope $end
$scope module relu_act $end
$var wire 1 ( clk $end
$var wire 32 7" x [31:0] $end
$var reg 16 8" out [15:0] $end
$upscope $end
$upscope $end
$upscope $end
$upscope $end
$enddefinitions $end

#0
$dumpvars
0!
bx !!
bx !"
1"
x"!
bx ""
0#
bx #!
bx #"
b0 $
bx $!
bx $"
bx %
bx %!
x%"
bx &
bx &!
0&"
bx '
bx '!
bx '"
0(
b11111110001011110000000000000000 (!
x("
1)
x)!
bx )"
0*
x*!
bx *"
b0 +
x+!
bx +"
bx ,
bx ,!
bx ,"
x-
x-!
bx -"
0.
x.!
b100010111000000000000000000 ."
bx /
bx /!
x/"
x0
bx 0!
x0"
bx 1
bx 1!
x1"
bx 2
bx 2!
bx 2"
bx 3
x3!
x3"
bx 4
04!
x4"
bx 5
bx 5!
bx 5"
b11111100110000100000000000000000 6
x6!
bx 6"
x7
bx 7!
bx 7"
x8
bx 8!
bx 8"
x9
bx 9!
bx :
bx :!
x;
bx ;!
x<
b11111111000100110000000000000000 <!
bx =
x=!
bx >
x>!
bx ?
x?!
bx @
bx @!
xA
xA!
0B
xB!
bx C
bx C!
xD
bx D!
bx E
bx E!
bx F
bx F!
bx G
xG!
bx H
0H!
bx I
bx I!
b11111111000001100000000000000000 J
xJ!
xK
bx K!
xL
bx L!
xM
bx M!
bx N
bx N!
xO
bx O!
xP
b11111011010001000000000000000000 P!
bx Q
xQ!
bx R
xR!
bx S
xS!
bx T
bx T!
xU
xU!
0V
xV!
bx W
bx W!
xX
bx X!
bx Y
bx Y!
bx Z
bx Z!
bx [
x[!
bx \
0\!
bx ]
bx ]!
b111011100000000000000000000 ^
x^!
x_
bx _!
x`
bx `!
xa
bx a!
bx b
bx b!
xc
bx c!
xd
b11111001101011110000000000000000 d!
bx e
xe!
bx f
xf!
bx g
xg!
bx h
bx h!
xi
xi!
0j
xj!
bx k
bx k!
xl
bx l!
bx m
bx m!
bx n
bx n!
bx o
xo!
bx p
0p!
bx q
bx q!
b11111011011011000000000000000000 r
xr!
xs
bx s!
xt
bx t!
xu
bx u!
bx v
bx v!
xw
bx w!
xx
b100101110100000000000000000 x!
bx y
xy!
bx z
xz!
bx {
x{!
bx |
bx |!
x}
x}!
0~
x~!
$end

#5000
1!
b0 !"
b0 #"
b11111110001011110000000000000000 $!
b0 $"
b0 %
b0 %!
b0 '!
1(
0)!
b100010111000000000000000000 *"
b0 +"
b0 ,
b0 ,!
b0 -"
b0 /!
0/"
b0 1!
b11111100110000100000000000000000 2
b0 2!
b0 2"
b0 3
b0 5
b0 5"
07
b0 7"
b11111111000100110000000000000000 8!
b0 8"
b0 9!
b0 :
b0 ;!
b0 =
0=!
b0 ?
b0 @
b0 @!
b0 C!
b0 E!
b11111111000001100000000000000000 F
b0 F!
b0 G
b0 I
0K
b11111011010001000000000000000000 L!
b0 M!
b0 N
b0 O!
b0 Q
0Q!
b0 S
b0 T
b0 T!
b0 W!
b0 Y!
b111011100000000000000000000 Z
b0 Z!
b0 [
b0 ]
0_
b11111001101011110000000000000000 `!
b0 a!
b0 b
b0 c!
b0 e
0e!
b0 g
b0 h
b0 h!
b0 k!
b0 m!
b11111011011011000000000000000000 n
b0 n!
b0 o
b0 q
0s
b100101110100000000000000000 t!
b0 u!
b0 v
b0 w!
b0 y
0y!
b0 {
b0 |
b0 |!

#10000
0!
0(

#15000
1!
0"!
1(
0("
0*!
0+!
00
00"
01"
06!
08
09
0>!
0?!
0D
0J!
0L
0M
0R!
0S!
0X
0^!
0`
0a
0f!
0g!
0l
0r!
0t
0u
0z!
0{!

#20000
0!
0(

#25000
1!
0%"
b0 &
1(
0-
0-!
03!
03"
0;
0A
0A!
0G!
0O
0U
0U!
0[!
0c
0i
0i!
0o!
0w
0}
0}!

#30000
0!
0(

#35000
1!
1(
0.!
04"
0<
0B!
0P
0V!
0d
0j!
0x
0~!

#40000
0!
0(

#45000
1!
1(

#50000
0!
0"
0(
0)

#55000
1!
1(

#60000
0!
0(

#65000
1!
1(

#70000
0!
0(

#75000
1!
1(

#80000
0!
0(

#85000
1!
1(

#90000
0!
0(

#95000
1!
1(

#100000
0!
1#
b1 $
1&"
b0 '
0(
1*
b1 +
1.
14!
1B
1H!
1V
1\!
1j
1p!
1~

#105000
1!
b11110010100 !!
b1 !"
b1111110001 ""
b1 %!
b1111011111011001 '"
1(
1)!
b1 +"
b1 ,!
b100101010000 /
b1 /!
1/"
b11110010100 0!
b1 2"
b1 3
b1111011100001101 5!
b1 5"
b1111011111011001 6"
17
b1 9!
b1 :
b1 =
1=!
b100101010000 >
b1 @!
b1111011001001011 C
b1 C!
b1111011100001101 D!
b1 G
b10110001001 I!
1K
b1 M!
b1 N
b1 Q
1Q!
b1111011001001011 R
b1 T!
b1111011001000000 W
b1 W!
b10110001001 X!
b1 [
b1111011001001110 ]!
1_
b1 a!
b1 b
b1 e
1e!
b1111011001000000 f
b1 h!
b10001000011 k
b1 k!
b1111011001001110 l!
b1 o
b1111110001 q!
1s
b1 u!
b1 v
b1 y
1y!
b10001000011 z
b1 |!

#110000
0!
b10 $
b1 '
0(
b10 +

