custom_nn_implementation/custom_nn_implementation.srcs/sources_1/new/relu.v
module relu #(
  parameter DATAWIDTH      = 16,
  parameter WEIGHTINTWIDTH = 4
)(
  input                        clk,
  input      [2*DATAWIDTH-1:0] x,
  output reg [DATAWIDTH-1:0]   out
);

always @(posedge clk) begin
  if ($signed(x) >= 0) begin
    if (|x[2*DATAWIDTH-1 -: WEIGHTINTWIDTH+1]) 
      out <= {1'b0, {(DATAWIDTH-1){1'b1}}};    
    else
      out <= x[2*DATAWIDTH-1 - WEIGHTINTWIDTH -: DATAWIDTH];
  end else begin
    out <= 0;
  end
end

endmodule

custom_nn_implementation/custom_nn_implementation.srcs/sources_1/new/weight_memory.v
`timescale 1ns / 1ps

module weight_memory #(
  parameter NUMWEIGHT     = 3,
  parameter NEURONNO      = 5,
  parameter LAYERNO       = 1,
  parameter ADDRESSWIDTH  = 10,
  parameter DATAWIDTH     = 16,
  parameter WEIGHTFILE    = "w_1_15.mif"
)(
  input                         clk,
  input                         ren,
  input      [ADDRESSWIDTH-1:0] radd,
  output reg [DATAWIDTH-1:0]    wout
);

  reg [DATAWIDTH-1:0] mem [0:NUMWEIGHT-1];

  initial begin
    $readmemb(WEIGHTFILE, mem);
  end

  always @(posedge clk) begin
    if (ren) begin
      wout <= mem[radd];
    end
  end

endmodule

custom_nn_implementation/custom_nn_implementation.srcs/sources_1/new/neuron_1.v
`timescale 1ns / 1ps

module neuron #(
  parameter NUM_INPUTS      = 784,
  parameter DATAWIDTH       = 16,
  parameter WEIGHTINTWIDTH  = 1,
  parameter BIAS            = 0,
  parameter WEIGHTFILE      = ""
)(
  input                      clk,
  input                      rst,
  input  [DATAWIDTH-1:0]     input_val,
  input                      input_valid,
  output [DATAWIDTH-1:0]     out,
  output reg                 out_valid
);

  localparam ADDR_WIDTH = $clog2(NUM_INPUTS);
  
  wire                       read_en;
  wire [DATAWIDTH-1:0]       weight;
  wire                       mux_valid;
  wire [2*DATAWIDTH:0]       combo_sum;
  wire [2*DATAWIDTH:0]       biased_sum;
  
  reg  [ADDR_WIDTH:0]        input_index;
  (* use_dsp48 = "yes" *)reg  [2*DATAWIDTH-1:0]     product;
  reg  [2*DATAWIDTH-1:0]     sum;
  reg  [2*DATAWIDTH-1:0]     bias;
  reg                        input_valid_d1;
  reg                        input_valid_d2;
  reg                        sigvalid;
  reg  [DATAWIDTH-1:0]       input_reg;
  reg                        muxvalid_d;
  reg                        muxvalid_f;              // end_of_dot_d
  
  initial begin
    bias = {BIAS[DATAWIDTH-1:0], {DATAWIDTH{1'b0}}};
  end

  assign read_en    = input_valid;
  assign combo_sum  = sum + product;
  assign biased_sum = sum + bias;
  assign mux_valid  = input_valid_d2;
  
  always @(posedge clk) begin
    if (rst | out_valid)
      input_index <= 0;
    else if (input_valid)
      input_index <= input_index + 1;
  end
  
  always @(posedge clk) begin
    product <= $signed(input_reg) * $signed(weight);
  end
  
  always @(posedge clk) begin
    if (rst | out_valid) begin
      sum <= 0;
    end
    else if ((input_index == NUM_INPUTS) && muxvalid_f) begin
      sum <= (biased_sum[2*DATAWIDTH] != biased_sum[2*DATAWIDTH-1]) ? {biased_sum[2*DATAWIDTH], {2*DATAWIDTH-1{biased_sum[2*DATAWIDTH-1]}}} : biased_sum;
    end
    else if (mux_valid) begin
      sum <= (combo_sum[2*DATAWIDTH] != combo_sum[2*DATAWIDTH-1]) ? {combo_sum[2*DATAWIDTH], {2*DATAWIDTH-1{combo_sum[2*DATAWIDTH-1]}}} : combo_sum;
    end
  end
  
  always @(posedge clk) begin
    input_reg      <= input_val;
    input_valid_d1 <= input_valid;
    input_valid_d2 <= input_valid_d1;
    
    sigvalid       <= ((input_index == NUM_INPUTS) & muxvalid_f);
    out_valid      <= sigvalid;
    muxvalid_d     <= mux_valid;
    muxvalid_f     <= !mux_valid & muxvalid_d;
    
  end
  
  weight_memory #(
    .NUMWEIGHT     (NUM_INPUTS),
    .ADDRESSWIDTH  (ADDR_WIDTH),
    .DATAWIDTH     (DATAWIDTH),
    .WEIGHTFILE    (WEIGHTFILE)
  ) weight_mem (
    .clk           (clk),
    .ren           (read_en),
    .radd          (input_index),
    .wout          (weight)
  );

  relu #(
    .DATAWIDTH      (DATAWIDTH),
    .WEIGHTINTWIDTH (WEIGHTINTWIDTH)
  ) relu_act (
    .clk            (clk),
    .x              (sum),
    .out            (out)
  );
  
endmodule

sim/new/tb_neuron.v
`timescale 1ns / 1ps

module tb_neuron;

  // Parameters matching the new neuron interface
  localparam DATAWIDTH       = 16;
  localparam NUM_INPUTS      = 4;        // Reduced for simulation efficiency
  localparam WEIGHTINTWIDTH  = 4;
  localparam BIAS            = 16'd1;   // Fixed bias value
  localparam WEIGHTFILE      = "test_weights.mif";
  
  // Clock and Reset
  reg                       clk;
  reg                       rst;
  
  // Neuron Interface (simplified)
  reg                       input_valid;
  reg  [DATAWIDTH-1:0]      input_val;
  wire [DATAWIDTH-1:0]      out;
  wire                      out_valid;
  
  // Test variables
  integer i;
  integer f;
  
  reg [DATAWIDTH-1:0] test_inputs [0:NUM_INPUTS-1];
  
  // Instantiate the Neuron
  neuron #(
    .NUM_INPUTS     (NUM_INPUTS),
    .DATAWIDTH      (DATAWIDTH),
    .WEIGHTINTWIDTH (WEIGHTINTWIDTH),
    .BIAS           (BIAS),
    .WEIGHTFILE     (WEIGHTFILE)
  ) uut (
    .clk            (clk),
    .rst            (rst),
    .input_val      (input_val),
    .input_valid    (input_valid),
    .out            (out),
    .out_valid      (out_valid)
  );
  
  // Clock generation
  always #5 clk = ~clk;
  
  // Initialize test vectors
  initial begin
    // Simple test vectors (1, 2, 3, 4)
    test_inputs[0] = 16'd1;
    test_inputs[1] = 16'd2;
    test_inputs[2] = 16'd3;
    test_inputs[3] = 16'd4;
  end
  
  // Create weight file for the test
  initial begin
    f = $fopen(WEIGHTFILE, "w");
    if (f) begin
      for (integer i = 0; i < NUM_INPUTS; i = i + 1) begin
        // Write weight value 1 for all weights (16-bit binary)
        $fwrite(f, "0000000000000001\n"); 
      end
      $fclose(f);
    end else begin
      $display("Error: Could not create weight file!");
      $finish;
    end
  end
  
  // Main test sequence
  initial begin
    // Initialize inputs
    clk         = 0;
    rst         = 1;
    input_val   = 0;
    input_valid = 0;
    
    // Reset the system
    #20;
    rst = 0;
    #20;
    
    // Test 1: Send inputs
    $display("Sending inputs...");
    for (i = 0; i < NUM_INPUTS; i = i + 1) begin
      input_val = test_inputs[i];
      input_valid = 1;
      #10;
    end
    input_valid = 0;
    
    // Wait for output
    wait(out_valid);
    $display("Output valid! Result = %h (Decimal: %0d)", out, $signed(out));
    
    // Verify result
    // Expected calculation:
    // Accumulator = (1*1 + 2*1 + 3*1 + 4*1) + (16 << 16)
    //             = 10 + 1,048,576 = 1,048,586 (0x0010000A)
    // ReLU output: bits [31:16] = 0x0010 = 16
    if (out !== 16) begin
      $display("ERROR: Expected 16 (0x001A), got %0d (0x%h)", $signed(out), out);
    end else begin
      $display("SUCCESS: Correct output received");
    end
    
    // End simulation
    #100 $display("Test completed!");
    $finish;
  end
  
  // Monitor to track important signals
  initial begin
    $timeformat(-9, 2, " ns", 6);
    $monitor("At %t: input_val=%0d, input_valid=%b, out=%0d, out_valid=%b",
             $time, $signed(input_val), input_valid, $signed(out), out_valid);
  end
  
  // Waveform dumping
  initial begin
    $dumpfile("tb_neuron.vcd");
    $dumpvars(0, tb_neuron);
  end
endmodule

custom_nn_implementation/custom_nn_implementation.sim/sim_1/behav/xsim/tb_neuron.vcd
$date
   Tue Aug  5 23:23:40 2025
$end

$version
  2023.2
  $dumpfile ("tb_neuron.vcd") 
$end

$timescale
  1ps
$end

$scope module tb_neuron $end
$var reg 1 ! clk $end
$var reg 1 " rst $end
$var reg 1 # input_valid $end
$var reg 16 $ input_val [15:0] $end
$var wire 16 % out [15:0] $end
$var wire 1 & out_valid $end
$var integer 32 ' i [31:0] $end
$var integer 32 ( f [31:0] $end
$scope module uut $end
$var wire 1 ) clk $end
$var wire 1 * rst $end
$var wire 16 + input_val [15:0] $end
$var wire 1 , input_valid $end
$var wire 16 % out [15:0] $end
$var reg 1 - out_valid $end
$var wire 1 . read_en $end
$var wire 16 / weight [15:0] $end
$var wire 1 0 mux_valid $end
$var wire 33 1 combo_sum [32:0] $end
$var wire 33 2 biased_sum [32:0] $end
$var reg 3 3 input_index [2:0] $end
$var reg 32 4 product [31:0] $end
$var reg 32 5 sum [31:0] $end
$var reg 32 6 bias [31:0] $end
$var reg 1 7 input_valid_d1 $end
$var reg 1 8 input_valid_d2 $end
$var reg 1 9 sigvalid $end
$var reg 16 : input_reg [15:0] $end
$var reg 1 ; muxvalid_d $end
$var reg 1 < muxvalid_f $end
$scope module weight_mem $end
$var wire 1 ) clk $end
$var wire 1 . ren $end
$var wire 2 = radd [1:0] $end
$var reg 16 > wout [15:0] $end
$upscope $end
$scope module relu_act $end
$var wire 1 ) clk $end
$var wire 32 ? x [31:0] $end
$var reg 16 @ out [15:0] $end
$upscope $end
$upscope $end
$scope begin Block60_11 $end
$var integer 32 A i [31:0] $end
$upscope $end
$upscope $end
$enddefinitions $end

#0
$dumpvars
0!
1"
0#
b0 $
bx %
x&
bx '
b11111111111111111011000111100000 (
0)
1*
b0 +
0,
x-
0.
bx /
x0
bx 1
bx 2
bx 3
bx 4
bx 5
b10000000000000000 6
x7
x8
x9
bx :
x;
x<
bx =
bx >
bx ?
bx @
b100 A
$end

#5000
1!
b0 %
1)
b10000000000000000 2
b0 3
b0 5
07
b0 :
b0 =
b0 ?
b0 @

#10000
0!
0)

#15000
1!
1)
00
08
09

#20000
0!
0"
0)
0*

#25000
1!
0&
1)
0-
0;

#30000
0!
0)

#35000
1!
1)
0<

#40000
0!
1#
b1 $
b0 '
0)
b1 +
1,
1.

#45000
1!
1)
b1 /
b1 3
17
b1 :
b1 =
b1 >

#50000
0!
b10 $
b1 '
0)
b10 +

#55000
1!
1)
10
b1 1
b10 3
b1 4
18
b10 :
b10 =

#60000
0!
b11 $
b10 '
0)
b11 +

#65000
1!
1)
b11 1
b10000000000000001 2
b11 3
b10 4
b1 5
b11 :
1;
b11 =
b1 ?

#70000
0!
b100 $
b11 '
0)
b100 +

#75000
1!
1)
b110 1
b10000000000000011 2
b100 3
b11 4
b11 5
b100 :
b0 =
b11 ?

#80000
0!
0#
b100 '
0)
0,
0.

#85000
1!
1)
b1010 1
b10000000000000110 2
b100 4
b110 5
07
b110 ?

#90000
0!
0)

#95000
1!
1)
00
b1110 1
b10000000000001010 2
b1010 5
08
b1010 ?

#100000
0!
0)

#105000
1!
1)
0;
1<

#110000
0!
0)

#115000
1!
1)
b10000000000001110 1
b100000000000001010 2
b10000000000001010 5
19
0<
b10000000000001010 ?

#120000
0!
0)

#125000
1!
b10000 %
1&
1)
1-
09
b10000 @

#130000
0!
0)

#135000
1!
0&
1)
0-
b100 1
b10000000000000000 2
b0 3
b0 5
b0 ?

#140000
0!
0)

#145000
1!
b0 %
1)
b0 @

